[
{
  "directory": "/home/launzoa/GitHub/Computer Vision/Digital Image Processing/interpolation/build",
  "command": "/usr/bin/c++  -I\"/home/launzoa/GitHub/Computer Vision/Digital Image Processing/interpolation/include\" -isystem /usr/include/opencv4  -o CMakeFiles/app.dir/src/main.cpp.o -c \"/home/launzoa/GitHub/Computer Vision/Digital Image Processing/interpolation/src/main.cpp\"",
  "file": "/home/launzoa/GitHub/Computer Vision/Digital Image Processing/interpolation/src/main.cpp",
  "output": "CMakeFiles/app.dir/src/main.cpp.o"
},
{
  "directory": "/home/launzoa/GitHub/Computer Vision/Digital Image Processing/interpolation/build",
  "command": "/usr/bin/c++  -I\"/home/launzoa/GitHub/Computer Vision/Digital Image Processing/interpolation/include\" -isystem /usr/include/opencv4  -o CMakeFiles/app.dir/src/interpolations.cpp.o -c \"/home/launzoa/GitHub/Computer Vision/Digital Image Processing/interpolation/src/interpolations.cpp\"",
  "file": "/home/launzoa/GitHub/Computer Vision/Digital Image Processing/interpolation/src/interpolations.cpp",
  "output": "CMakeFiles/app.dir/src/interpolations.cpp.o"
}
]